{
  "status": "active",
  "network_type": "testnet",
  "chain_id": "akash-testnet-6",
  "bech32_prefix": "akash",
  "codebase": {
    "version": "v0.12.1",
    "git_repo": "github.com/ovrclk/akash",
    "git_branch": "mainnet/main"
  },
  "faucet": {
    "url": "https://akash.vitwit.com/faucet"
  },
  "peers": {
    "seeds": [],
    "persistent_peers": [
      "2b027ca96b51ab4f3c69ac54fd05b7ae082fa6a8@147.75.32.11:26656",
      "036cbb0a1e11f9cafa54623b18761b094944d1ee@147.75.32.35:26656"
    ]
  },
  "apis": {
    "rpc_addrs": [
      "http://147.75.32.35:26657", 
      "http://147.75.32.11:26657"
    ],
    "rest_addrs": [
      "http://147.75.32.11:1317", 
      "http://147.75.32.35:1317"
    ]
  }
}
